{"_class":"com.tikal.jenkins.plugins.multijob.MultiJobBuild","actions":[{"_class":"hudson.model.CauseAction","causes":[{"_class":"hudson.model.Cause$UserIdCause","shortDescription":"Started by user Yagiz Nizipli","userId":"anonrig","userName":"Yagiz Nizipli"}]},{"_class":"hudson.model.ParametersAction","parameters":[{"_class":"hudson.model.BooleanParameterValue","name":"CERTIFY_SAFE","value":true},{"_class":"hudson.model.StringParameterValue","name":"COMMIT_SHA_CHECK","value":"3677ec460e56c6ddc2bc4834a28fc005caf03608"},{"_class":"hudson.model.StringParameterValue","name":"TARGET_GITHUB_ORG","value":"nodejs"},{"_class":"hudson.model.StringParameterValue","name":"TARGET_REPO_NAME","value":"node"},{"_class":"hudson.model.StringParameterValue","name":"PR_ID","value":"57943"},{"_class":"hudson.model.StringParameterValue","name":"REBASE_ONTO","value":"<pr base branch>"},{"_class":"com.wangyin.parameter.WHideParameterValue","name":"DESCRIPTION_SETTER_DESCRIPTION","value":""}]},{"_class":"hudson.model.ParametersAction","parameters":[{"_class":"hudson.model.StringParameterValue","name":"DESCRIPTION_SETTER_DESCRIPTION","value":"Testing <a href=https://github.com/nodejs/node/pull/57943>57943</a>"}]},{},{"_class":"hudson.model.CauseAction","causes":[{"_class":"com.tikal.jenkins.plugins.multijob.ResumeCause","shortDescription":"Resume build <a href=\"#job/node-test-pull-request/\">#66,374</a>","upstreamBuild":66374,"upstreamProject":"node-test-pull-request","upstreamUrl":"job/node-test-pull-request/"}]},{},{},{},{},{"_class":"hudson.plugins.git.util.BuildData","buildsByBranchName":{"refs/remotes/origin/_jenkins_local_branch":{"_class":"hudson.plugins.git.util.Build","buildNumber":66379,"buildResult":null,"marked":{},"revision":{}}},"lastBuiltRevision":{"SHA1":"3677ec460e56c6ddc2bc4834a28fc005caf03608","branch":[{}]},"remoteUrls":["git@github.com:$TARGET_GITHUB_ORG/$TARGET_REPO_NAME.git"],"scmName":""},{},{},{},{},{"_class":"hudson.model.ParametersAction","parameters":[{"_class":"hudson.model.StringParameterValue","name":"DESCRIPTION_SETTER_DESCRIPTION","value":"Testing <a href=https://github.com/nodejs/node/pull/57943>57943</a>"}]},{"_class":"hudson.plugins.parameterizedtrigger.BuildInfoExporterAction","triggeredBuilds":[],"triggeredProjects":[null]},{"_class":"com.tikal.jenkins.plugins.multijob.MultiJobTestResults","failCount":0,"skipCount":0,"totalCount":0,"urlName":"testReport","childReports":[]},{},{},{},{},{},{},{},{},{},{},{"_class":"org.jenkinsci.plugins.displayurlapi.actions.RunDisplayAction","artifactsUrl":"https://ci.nodejs.org/job/node-test-pull-request/66379/artifact","changesUrl":"https://ci.nodejs.org/job/node-test-pull-request/changes","displayUrl":"https://ci.nodejs.org/job/node-test-pull-request/66379/","testsUrl":"https://ci.nodejs.org/job/node-test-pull-request/66379/testReport"}],"id":"66379","result":"FAILURE","timestamp":1745160390691,"subBuilds":[{"build":{"_class":"com.tikal.jenkins.plugins.multijob.MultiJobBuild","result":"FAILURE","subBuilds":[{"buildNumber":59822,"jobName":"node-test-linter","result":"SUCCESS"},{"buildNumber":59824,"jobName":"node-test-commit-freebsd","result":"SUCCESS"},{"buildNumber":64681,"jobName":"node-test-commit-osx","result":"SUCCESS"},{"buildNumber":58641,"jobName":"node-test-commit-plinux","result":"SUCCESS"},{"buildNumber":60266,"jobName":"node-test-commit-smartos","result":"SUCCESS"},{"buildNumber":58166,"jobName":"node-test-commit-arm","result":"SUCCESS"},{"buildNumber":49073,"jobName":"node-test-commit-linuxone","result":"SUCCESS"},{"buildNumber":56894,"jobName":"node-test-commit-aix","result":"SUCCESS"},{"buildNumber":42361,"jobName":"node-test-commit-arm-fanned","result":"SUCCESS"},{"buildNumber":41807,"jobName":"node-test-commit-custom-suites-freestyle","result":"SUCCESS"},{"buildNumber":64224,"jobName":"node-test-commit-linux","result":"SUCCESS"},{"buildNumber":18143,"jobName":"node-test-commit-arm-debug","result":"FAILURE"},{"buildNumber":50204,"jobName":"node-test-commit-linux-containered","result":"FAILURE"},{"buildNumber":69897,"jobName":"node-test-commit-windows-fanned","result":"UNSTABLE","phases":[{"jobName":"git-rebase","result":"SUCCESS"},{"jobName":"node-compile-windows","result":"SUCCESS"},{"jobName":"node-compile-windows-debug","result":"SUCCESS"},{"jobName":"node-test-binary-windows-native-suites","result":"SUCCESS"},{"jobName":"node-test-binary-windows-js-suites","result":"UNSTABLE"}]}]},"jobName":"node-test-commit"}]}