{"_class":"com.tikal.jenkins.plugins.multijob.MultiJobBuild","actions":[{"_class":"hudson.model.ParametersAction","parameters":[{"_class":"hudson.model.BooleanParameterValue","name":"CERTIFY_SAFE","value":true},{"_class":"hudson.model.StringParameterValue","name":"COMMIT_SHA_CHECK","value":"6509a5e27b0556a6de4fa1c74deebbbf71084798"},{"_class":"hudson.model.StringParameterValue","name":"TARGET_GITHUB_ORG","value":"nodejs"},{"_class":"hudson.model.StringParameterValue","name":"TARGET_REPO_NAME","value":"node"},{"_class":"hudson.model.StringParameterValue","name":"PR_ID","value":"59432"},{"_class":"hudson.model.StringParameterValue","name":"REBASE_ONTO","value":"<pr base branch>"},{"_class":"com.wangyin.parameter.WHideParameterValue","name":"DESCRIPTION_SETTER_DESCRIPTION","value":""}]},{"_class":"hudson.model.CauseAction","causes":[{"_class":"hudson.model.Cause$UserIdCause","shortDescription":"Started by user Node.js GitHub Bot","userId":"nodejs-github-bot","userName":"Node.js GitHub Bot"}]},{},{},{},{},{"_class":"hudson.plugins.git.util.BuildData","buildsByBranchName":{"refs/remotes/origin/_jenkins_local_branch":{"_class":"hudson.plugins.git.util.Build","buildNumber":69609,"buildResult":null,"marked":{},"revision":{}}},"lastBuiltRevision":{"SHA1":"6509a5e27b0556a6de4fa1c74deebbbf71084798","branch":[{}]},"remoteUrls":["git@github.com:$TARGET_GITHUB_ORG/$TARGET_REPO_NAME.git"],"scmName":""},{},{},{},{"_class":"hudson.model.ParametersAction","parameters":[{"_class":"hudson.model.StringParameterValue","name":"DESCRIPTION_SETTER_DESCRIPTION","value":"Testing <a href=https://github.com/nodejs/node/pull/59432>59432</a>"}]},{"_class":"hudson.plugins.parameterizedtrigger.BuildInfoExporterAction","triggeredBuilds":[],"triggeredProjects":[null]},{"_class":"com.tikal.jenkins.plugins.multijob.MultiJobTestResults","failCount":0,"skipCount":0,"totalCount":0,"urlName":"testReport","childReports":[]},{},{},{},{},{},{},{},{},{},{},{"_class":"org.jenkinsci.plugins.displayurlapi.actions.RunDisplayAction","artifactsUrl":"https://ci.nodejs.org/job/node-test-pull-request/69609/artifact","changesUrl":"https://ci.nodejs.org/job/node-test-pull-request/changes","displayUrl":"https://ci.nodejs.org/job/node-test-pull-request/69609/","testsUrl":"https://ci.nodejs.org/job/node-test-pull-request/69609/testReport"}],"id":"69609","result":"FAILURE","timestamp":1759907937963,"subBuilds":[{"build":{"_class":"com.tikal.jenkins.plugins.multijob.MultiJobBuild","result":"FAILURE","subBuilds":[{"buildNumber":62147,"jobName":"node-test-commit-freebsd","result":"SUCCESS"},{"buildNumber":66909,"jobName":"node-test-commit-linux","result":"SUCCESS"},{"buildNumber":62121,"jobName":"node-test-linter","result":"SUCCESS"},{"buildNumber":67219,"jobName":"node-test-commit-osx","result":"UNSTABLE"},{"buildNumber":62750,"jobName":"node-test-commit-smartos","result":"UNSTABLE"},{"buildNumber":61071,"jobName":"node-test-commit-plinux","result":"SUCCESS"},{"buildNumber":53077,"jobName":"node-test-commit-linux-containered","result":"FAILURE"},{"buildNumber":60650,"jobName":"node-test-commit-arm","result":"SUCCESS"},{"buildNumber":51880,"jobName":"node-test-commit-linuxone","result":"SUCCESS"},{"buildNumber":20629,"jobName":"node-test-commit-arm-debug","result":"SUCCESS"},{"buildNumber":59333,"jobName":"node-test-commit-aix","result":"SUCCESS"},{"buildNumber":73462,"jobName":"node-test-commit-windows-fanned","result":"SUCCESS"},{"buildNumber":44327,"jobName":"node-test-commit-custom-suites-freestyle","result":"SUCCESS"},{"buildNumber":44695,"jobName":"node-test-commit-arm-fanned","result":"SUCCESS"}]},"jobName":"node-test-commit"}]}